services/__init__.py
services/slack_service.py
services/teams_service.py
python_postx-1.0.4.dist-info/LICENSE
python_postx-1.0.4.dist-info/METADATA
python_postx-1.0.4.dist-info/WHEEL
python_postx-1.0.4.dist-info/top_level.txt
python_postx-1.0.4.dist-info/RECORD
