Metadata-Version: 2.1
Name: python-postx
Version: 1.0.4
Summary: PostX is a package that provides a simple interface for posting messages to multiple platforms.
Home-page: https://gitlab.com/mediatech15/python-postx
Author: Kyle Mason
License: UNKNOWN
Project-URL: Bug Tracker, https://gitlab.com/mediatech15/python-postx/-/issues
Keywords: messaging,slack,teams,messages
Platform: UNKNOWN
Classifier: Programming Language :: Python :: 3 :: Only
Classifier: Programming Language :: Python :: 3.6
Classifier: Programming Language :: Python :: 3.7
Classifier: Programming Language :: Python :: 3.8
Classifier: Programming Language :: Python :: 3.9
Classifier: Programming Language :: Python :: 3.10
Classifier: License :: OSI Approved :: MIT License
Classifier: Operating System :: OS Independent
Classifier: Development Status :: 5 - Production/Stable
Requires-Python: >=3.6
Requires-Dist: requests (>=2.25.0)
